cbl/__init__.py
cbl/cbl_collection.py
cbl/cbl_replicator.py
cbl/couchbase_lite.py
cbl/libs/arm64-v8a/couchbase_lite_cffi.so
cbl/libs/arm64-v8a/libcblite.so
cbl/libs/armeabi-v7a/couchbase_lite_cffi.so
cbl/libs/armeabi-v7a/libcblite.so
couchbaselitepython-3.2.4.0.dist-info/METADATA
couchbaselitepython-3.2.4.0.dist-info/WHEEL
couchbaselitepython-3.2.4.0.dist-info/top_level.txt
couchbaselitepython-3.2.4.0.dist-info/RECORD
