Metadata-Version: 2.4
Name: CouchbaseLitePython
Version: 3.2.4.0
Summary: Couchbase Lite in CFFI bindings
Author: Jhay Mendoza
Author-email: jrockhackerz@example.com
Classifier: Programming Language :: Python :: 3
Classifier: Operating System :: Android
Dynamic: author
Dynamic: author-email
Dynamic: classifier
Dynamic: summary
